octoprint_smsnotifier/__init__.py
octoprint_smsnotifier/templates/smsnotifier_settings.jinja2
OctoPrint_Twilio-0.4.1.dist-info/LICENSE
OctoPrint_Twilio-0.4.1.dist-info/METADATA
OctoPrint_Twilio-0.4.1.dist-info/WHEEL
OctoPrint_Twilio-0.4.1.dist-info/entry_points.txt
OctoPrint_Twilio-0.4.1.dist-info/top_level.txt
OctoPrint_Twilio-0.4.1.dist-info/RECORD
