Metadata-Version: 2.1
Name: OctoPrint-Twilio
Version: 0.4.1
Summary: Receive SMS notifications when OctoPrint jobs are complete.
Home-page: https://github.com/taxilian/OctoPrint-Twilio
Author: Richard Bateman
Author-email: taxilian@gmail.com
License: AGPLv3
Platform: UNKNOWN
Requires-Dist: OctoPrint
Requires-Dist: twilio (>=6)
Requires-Dist: phonenumbers
Requires-Dist: cloudinary
Requires-Dist: six (>=1.9.0)
Requires-Dist: sarge
